adminAPI.py
app.py
backupServer.py
bpApp.py
commServer.py
daqbrokerDatabase.py
daqbrokerServer.py
daqbrokerSettings.py
dataAPI.py
instrumentsAPI.py
logServer.py
monitorServer.py
monitoringAPI.py
runsAPI.py
supportFuncs.py
DAQBrokerServer-0.0.2.dist-info/METADATA
DAQBrokerServer-0.0.2.dist-info/RECORD
DAQBrokerServer-0.0.2.dist-info/WHEEL
DAQBrokerServer-0.0.2.dist-info/top_level.txt
